SFDL_DB/__init__.py
SFDL_DB/skewing.py
sfdl_db-0.1.0.dist-info/METADATA
sfdl_db-0.1.0.dist-info/WHEEL
sfdl_db-0.1.0.dist-info/top_level.txt
sfdl_db-0.1.0.dist-info/RECORD
