Metadata-Version: 2.4
Name: SFDL_DB
Version: 0.1.0
Summary: Same Features, Different Label Skew Generator
Home-page: https://github.com/yourusername/SFDL_DB
Author: Your Name
Author-email: Your Name <your.email@example.com>
License: MIT
Project-URL: Homepage, https://github.com/yourusername/SFDL_DB
Requires-Python: >=3.6
Requires-Dist: pandas
Requires-Dist: matplotlib
Requires-Dist: scikit-learn
Dynamic: author
Dynamic: home-page
